{
  "allVideos": [
    {
      "id": "2",
      "caption": "thriller",
      "url": "https://th.bing.com/th/id/OIP.hLCEMv2HigSv3cVyx3vFeQHaHa?w=180&h=180&c=7&r=0&o=5&dpr=1.5&pid=1.7",
      "link": "https://www.youtube.com/embed/sOnqjkJTMaA"
    },
    {
      "id": "1",
      "caption": "thriller",
      "url": "https://th.bing.com/th/id/OIP.hLCEMv2HigSv3cVyx3vFeQHaHa?w=180&h=180&c=7&r=0&o=5&dpr=1.5&pid=1.7",
      "link": "https://www.youtube.com/embed/sOnqjkJTMaA"
    },
    {
      "id": "3",
      "caption": "thriller",
      "url": "https://th.bing.com/th/id/OIP.hLCEMv2HigSv3cVyx3vFeQHaHa?w=180&h=180&c=7&r=0&o=5&dpr=1.5&pid=1.7",
      "link": "https://www.youtube.com/embed/sOnqjkJTMaA"
    },
    {
      "id": "4",
      "caption": "thriller",
      "url": "https://th.bing.com/th/id/OIP.hLCEMv2HigSv3cVyx3vFeQHaHa?w=180&h=180&c=7&r=0&o=5&dpr=1.5&pid=1.7",
      "link": "https://www.youtube.com/embed/sOnqjkJTMaA"
    }
  ],
  "history": [
    {
      "caption": "thriller",
      "link": "https://www.youtube.com/embed/sOnqjkJTMaA",
      "timeStamp": "09/24/2024, 02:07:46 PM",
      "id": 5
    },
    {
      "caption": "BeatIt",
      "link": "https://www.youtube.com/embed/sOnqjkJTMaA",
      "timeStamp": "09/24/2024, 02:07:50 PM",
      "id": 6
    },
    {
      "caption": "thriller",
      "link": "https://www.youtube.com/embed/sOnqjkJTMaA",
      "timeStamp": "09/24/2024, 02:23:48 PM",
      "id": 7
    },
    {
      "caption": "BeatIt",
      "link": "https://www.youtube.com/embed/sOnqjkJTMaA",
      "timeStamp": "09/25/2024, 03:00:59 PM",
      "id": 8
    },
    {
      "caption": "BeatIt",
      "link": "https://www.youtube.com/embed/sOnqjkJTMaA",
      "timeStamp": "09/25/2024, 03:57:43 PM",
      "id": 9
    },
    {
      "caption": "thriller",
      "link": "https://www.youtube.com/embed/sOnqjkJTMaA",
      "timeStamp": "09/25/2024, 03:57:55 PM",
      "id": 10
    },
    {
      "caption": "thriller",
      "link": "https://www.youtube.com/embed/sOnqjkJTMaA",
      "timeStamp": "09/25/2024, 03:58:13 PM",
      "id": 11
    },
    {
      "caption": "thriller",
      "link": "https://www.youtube.com/embed/sOnqjkJTMaA",
      "timeStamp": "09/25/2024, 03:58:25 PM",
      "id": 12
    },
    {
      "caption": "thriller",
      "link": "https://www.youtube.com/embed/sOnqjkJTMaA",
      "timeStamp": "09/25/2024, 04:20:20 PM",
      "id": 13
    },
    {
      "caption": "thriller",
      "link": "https://www.youtube.com/embed/oRdxUFDoQe0",
      "timeStamp": "09/25/2024, 04:20:34 PM",
      "id": 14
    },
    {
      "caption": "thriller",
      "link": "https://www.youtube.com/embed/sOnqjkJTMaA",
      "timeStamp": "09/26/2024, 01:02:13 PM",
      "id": 15
    },
    {
      "caption": "thriller",
      "link": "https://www.youtube.com/embed/sOnqjkJTMaA",
      "timeStamp": "09/26/2024, 03:26:26 PM",
      "id": 16
    },
    {
      "caption": "thriller",
      "link": "https://www.youtube.com/embed/sOnqjkJTMaA",
      "timeStamp": "09/26/2024, 03:45:23 PM",
      "id": 17
    }
  ],
  "category": [
    {
      "id": 1,
      "categoryName": "movie",
      "allVideos": [
        {
          "id": "1",
          "caption": "thriller",
          "url": "https://th.bing.com/th/id/OIP.hLCEMv2HigSv3cVyx3vFeQHaHa?w=180&h=180&c=7&r=0&o=5&dpr=1.5&pid=1.7",
          "link": "https://www.youtube.com/embed/sOnqjkJTMaA"
        }
      ]
    }
  ]
}